papyru/__init__.py
papyru/auth.py
papyru/context.py
papyru/logger.py
papyru/middleware.py
papyru/problem.py
papyru/profiler.py
papyru/resource.py
papyru/serializer.py
papyru/test.py
papyru/validation.py
papyru/xml_helper.py
papyru-0.0.1.dev31.dist-info/LICENSE.txt
papyru-0.0.1.dev31.dist-info/METADATA
papyru-0.0.1.dev31.dist-info/WHEEL
papyru-0.0.1.dev31.dist-info/top_level.txt
papyru-0.0.1.dev31.dist-info/RECORD
