Metadata-Version: 2.1
Name: papyru
Version: 0.0.1.dev31
Summary: minimal REST library with OpenAPI-based validation for django
Home-page: https://www.fotopuzzle.de/
Author: puzzle & play GmbH
Author-email: papyru@puzzleandplay.de
License: AGPLv3
Platform: any
Classifier: Development Status :: 3 - Alpha
Classifier: Intended Audience :: Developers
Classifier: Topic :: Internet :: WWW/HTTP
Classifier: License :: OSI Approved :: GNU Affero General Public License v3
Classifier: Programming Language :: Python :: 3.6
Requires-Dist: Cerberus
Requires-Dist: Django
Requires-Dist: bravado-core
Requires-Dist: bravado (<9.2)
Requires-Dist: pyyaml
